unicode_segmentation_rs-0.2.1.dist-info/METADATA
unicode_segmentation_rs-0.2.1.dist-info/WHEEL
unicode_segmentation_rs-0.2.1.dist-info/licenses/LICENSE
unicode_segmentation_rs/__init__.py
unicode_segmentation_rs/__init__.pyi
unicode_segmentation_rs/py.typed
unicode_segmentation_rs/unicode_segmentation_rs.abi3.so
unicode_segmentation_rs-0.2.1.dist-info/RECORD
