Metadata-Version: 2.4
Name: unicode-segmentation-rs
Version: 0.2.1
Classifier: Programming Language :: Rust
Classifier: Programming Language :: Python :: Implementation :: CPython
Classifier: Programming Language :: Python :: Implementation :: PyPy
Classifier: Topic :: Software Development :: Libraries :: Python Modules
License-File: LICENSE
Summary: Unicode segmentation and width for Python using Rust
Author-email: Michal Čihař <michal@weblate.org>
License-Expression: MIT
Requires-Python: >=3.10
Project-URL: Documentation, https://docs.weblate.org/
Project-URL: Download, https://github.com/WeblateOrg/unicode-segmentation-rs
Project-URL: Funding, https://weblate.org/donate/
Project-URL: Homepage, https://weblate.org/
Project-URL: Issue Tracker, https://github.com/WeblateOrg/unicode-segmentation-rs/issues
Project-URL: Source Code, https://github.com/WeblateOrg/unicode-segmentation-rs
Project-URL: Twitter, https://twitter.com/WeblateOrg
